ccswitcher/__init__.py
ccswitcher/cli.py
ccswitcher/config.py
ccswitcher-0.1.0.dist-info/licenses/LICENSE
ccswitcher-0.1.0.dist-info/METADATA
ccswitcher-0.1.0.dist-info/WHEEL
ccswitcher-0.1.0.dist-info/entry_points.txt
ccswitcher-0.1.0.dist-info/top_level.txt
ccswitcher-0.1.0.dist-info/RECORD
