Metadata-Version: 2.4
Name: ccswitcher
Version: 0.1.0
Summary: CLI tool to switch between different Claude Code API settings
Home-page: https://github.com/yourusername/ccswitcher
Author: CCswitcher Contributors
Requires-Python: >=3.7
License-File: LICENSE
Requires-Dist: click>=8.0.0
Requires-Dist: pyyaml>=5.0.0
Dynamic: author
Dynamic: home-page
Dynamic: license-file
Dynamic: requires-python
